<?xml version="1.0" encoding="utf-8"?>
<AppModuleSiteMap xmlns:xsi="http://www.w3.org/2001/XMLSchema-instance">
  <SiteMapUniqueName>appbase_LegislativeOperations</SiteMapUniqueName>
  <EnableCollapsibleGroups>False</EnableCollapsibleGroups>
  <ShowHome>True</ShowHome>
  <ShowPinned>True</ShowPinned>
  <ShowRecents>True</ShowRecents>
  <SiteMap IntroducedVersion="7.0.0.0">
    <Area Id="area_9a81503b" ResourceId="SitemapDesigner.NewTitle" DescriptionResourceId="SitemapDesigner.NewTitle" ShowGroups="true" IntroducedVersion="7.0.0.0">
      <Titles>
        <Title LCID="1033" Title="Constituent Interactions" />
      </Titles>
      <Group Id="group_9efad1d2" ResourceId="SitemapDesigner.NewGroup" DescriptionResourceId="SitemapDesigner.NewGroup" IntroducedVersion="7.0.0.0" IsProfile="false" ToolTipResourseId="SitemapDesigner.Unknown">
        <Titles>
          <Title LCID="1033" Title="Constituent Interactions" />
        </Titles>
        <SubArea Id="subarea_e30e4ee4" Icon="/_imgs/imagestrips/transparent_spacer.gif" Entity="appbase_externalinteraction" Client="All,Outlook,OutlookLaptopClient,OutlookWorkstationClient,Web" AvailableOffline="true" PassParams="false" Sku="All,OnPremise,Live,SPLA">
          <Titles>
            <Title LCID="1033" Title="Interactions" />
          </Titles>
        </SubArea>
        <SubArea Id="subarea_fddf0635" Icon="/_imgs/imagestrips/transparent_spacer.gif" Entity="queueitem" Client="All,Outlook,OutlookLaptopClient,OutlookWorkstationClient,Web" AvailableOffline="true" PassParams="false" Sku="All,OnPremise,Live,SPLA" />
      </Group>
      <Group Id="group_b9956c3f" ResourceId="SitemapDesigner.NewGroup" DescriptionResourceId="SitemapDesigner.NewGroup" IntroducedVersion="7.0.0.0" IsProfile="false" ToolTipResourseId="SitemapDesigner.Unknown">
        <Titles>
          <Title LCID="1033" Title="Activity Log" />
        </Titles>
        <SubArea Id="subarea_fcc1967e" Icon="/_imgs/imagestrips/transparent_spacer.gif" Entity="activitypointer" Client="All,Outlook,OutlookLaptopClient,OutlookWorkstationClient,Web" AvailableOffline="true" PassParams="false" Sku="All,OnPremise,Live,SPLA" />
        <SubArea Id="subarea_e63f3123" Icon="/_imgs/imagestrips/transparent_spacer.gif" Entity="appointment" Client="All,Outlook,OutlookLaptopClient,OutlookWorkstationClient,Web" AvailableOffline="true" PassParams="false" Sku="All,OnPremise,Live,SPLA" />
        <SubArea Id="subarea_828d923e" Icon="/_imgs/imagestrips/transparent_spacer.gif" Entity="email" Client="All,Outlook,OutlookLaptopClient,OutlookWorkstationClient,Web" AvailableOffline="true" PassParams="false" Sku="All,OnPremise,Live,SPLA" />
        <SubArea Id="subarea_2ca6cb49" Icon="/_imgs/imagestrips/transparent_spacer.gif" Entity="letter" Client="All,Outlook,OutlookLaptopClient,OutlookWorkstationClient,Web" AvailableOffline="true" PassParams="false" Sku="All,OnPremise,Live,SPLA" />
        <SubArea Id="subarea_5b272e8d" Icon="/_imgs/imagestrips/transparent_spacer.gif" Entity="phonecall" Client="All,Outlook,OutlookLaptopClient,OutlookWorkstationClient,Web" AvailableOffline="true" PassParams="false" Sku="All,OnPremise,Live,SPLA" />
        <SubArea Id="subarea_7cf326c7" Icon="/_imgs/imagestrips/transparent_spacer.gif" Entity="task" Client="All,Outlook,OutlookLaptopClient,OutlookWorkstationClient,Web" AvailableOffline="true" PassParams="false" Sku="All,OnPremise,Live,SPLA" />
      </Group>
      <Group Id="group_c38d12b0" ResourceId="SitemapDesigner.NewGroup" DescriptionResourceId="SitemapDesigner.NewGroup" IntroducedVersion="7.0.0.0" IsProfile="false" ToolTipResourseId="SitemapDesigner.Unknown">
        <Titles>
          <Title LCID="1033" Title="Admin" />
        </Titles>
        <SubArea Id="subarea_ae5f2da3" Icon="/_imgs/imagestrips/transparent_spacer.gif" Entity="queue" Client="All,Outlook,OutlookLaptopClient,OutlookWorkstationClient,Web" AvailableOffline="true" PassParams="false" Sku="All,OnPremise,Live,SPLA" />
        <SubArea Id="subarea_2c41a25e" Icon="/_imgs/imagestrips/transparent_spacer.gif" Entity="appbase_externalinteractionsource" Client="All,Outlook,OutlookLaptopClient,OutlookWorkstationClient,Web" AvailableOffline="true" PassParams="false" Sku="All,OnPremise,Live,SPLA">
          <Titles>
            <Title LCID="1033" Title="Interaction Sources" />
          </Titles>
        </SubArea>
        <SubArea Id="subarea_4e932df5" Icon="/_imgs/imagestrips/transparent_spacer.gif" Entity="appbase_externalinteractiontopic" Client="All,Outlook,OutlookLaptopClient,OutlookWorkstationClient,Web" AvailableOffline="true" PassParams="false" Sku="All,OnPremise,Live,SPLA">
          <Titles>
            <Title LCID="1033" Title="Interaction Topics" />
          </Titles>
        </SubArea>
      </Group>
    </Area>
  </SiteMap>
  <LocalizedNames>
    <LocalizedName description="Legislative Operations" languagecode="1033" />
  </LocalizedNames>
</AppModuleSiteMap>