<?xml version="1.0" encoding="utf-8"?>
<savedqueries xmlns:xsi="http://www.w3.org/2001/XMLSchema-instance">
  <savedquery>
    <IsCustomizable>1</IsCustomizable>
    <CanBeDeleted>0</CanBeDeleted>
    <isquickfindquery>0</isquickfindquery>
    <isprivate>0</isprivate>
    <isdefault>1</isdefault>
    <savedqueryid>{84559c9b-e97e-4961-aaf9-1606c8b760f2}</savedqueryid>
    <layoutxml>
      <grid name="resultset" jump="appbase_name" select="1" icon="1" preview="1">
        <row name="result" id="appbase_courtcaserepresentationid">
          <cell name="appbase_name" width="300" />
          <cell name="appbase_representationtype" width="156" />
          <cell name="appbase_representative" width="124" />
          <cell name="appbase_representativeorganization" width="200" />
          <cell name="appbase_isleadcounsel" width="131" />
          <cell name="appbase_startdate" width="100" />
          <cell name="appbase_enddate" width="100" />
          <cell name="appbase_contactemail" width="121" />
          <cell name="appbase_contactphone" width="123" />
          <cell name="appbase_barstate" width="100" />
          <cell name="appbase_barnumber" width="110" />
          <cell name="appbase_admissiondate" width="131" />
          <cell name="appbase_prohacvice" width="115" />
        </row>
      </grid>
    </layoutxml>
    <querytype>0</querytype>
    <fetchxml>
      <fetch version="1.0" mapping="logical">
        <entity name="appbase_courtcaserepresentation">
          <attribute name="appbase_courtcaserepresentationid" />
          <attribute name="appbase_name" />
          <order attribute="appbase_name" descending="false" />
          <filter type="and">
            <condition attribute="statecode" operator="eq" value="0" />
          </filter>
          <attribute name="appbase_representationtype" />
          <attribute name="appbase_representative" />
          <attribute name="appbase_representativeorganization" />
          <attribute name="appbase_isleadcounsel" />
          <attribute name="appbase_startdate" />
          <attribute name="appbase_enddate" />
          <attribute name="appbase_contactemail" />
          <attribute name="appbase_contactphone" />
          <attribute name="appbase_barstate" />
          <attribute name="appbase_barnumber" />
          <attribute name="appbase_admissiondate" />
          <attribute name="appbase_prohacvice" />
        </entity>
      </fetch>
    </fetchxml>
    <IntroducedVersion>1.0</IntroducedVersion>
    <LocalizedNames>
      <LocalizedName description="Active Court Case Representations" languagecode="1033" />
    </LocalizedNames>
  </savedquery>
</savedqueries>