<?xml version="1.0" encoding="utf-8"?>
<optionset Name="appbase_issueresolutionstatus" localizedName="Issue Resolution Status" xmlns:xsi="http://www.w3.org/2001/XMLSchema-instance">
  <OptionSetType>picklist</OptionSetType>
  <IsGlobal>1</IsGlobal>
  <IntroducedVersion>1.1.0.5</IntroducedVersion>
  <IsCustomizable>1</IsCustomizable>
  <displaynames>
    <displayname description="Issue Resolution Status" languagecode="1033" />
  </displaynames>
  <Descriptions>
    <Description description="" languagecode="1033" />
  </Descriptions>
  <options>
    <option value="147130181" ExternalValue="" IsHidden="0">
      <labels>
        <label description="New" languagecode="1033" />
      </labels>
      <Descriptions>
        <Description description="" languagecode="1033" />
      </Descriptions>
    </option>
    <option value="147130182" ExternalValue="" IsHidden="0">
      <labels>
        <label description="In Review" languagecode="1033" />
      </labels>
      <Descriptions>
        <Description description="" languagecode="1033" />
      </Descriptions>
    </option>
    <option value="147130188" IsHidden="0">
      <labels>
        <label description="Confirmed Issue" languagecode="1033" />
      </labels>
      <Descriptions>
        <Description description="" languagecode="1033" />
      </Descriptions>
    </option>
    <option value="147130183" ExternalValue="" IsHidden="0">
      <labels>
        <label description="Resolved" languagecode="1033" />
      </labels>
    </option>
    <option value="147130184" ExternalValue="" IsHidden="0">
      <labels>
        <label description="Mitigated" languagecode="1033" />
      </labels>
    </option>
    <option value="147130185" ExternalValue="" IsHidden="0">
      <labels>
        <label description="No Action Required" languagecode="1033" />
      </labels>
    </option>
    <option value="147130186" ExternalValue="" IsHidden="0">
      <labels>
        <label description="Closed as Unresolved" languagecode="1033" />
      </labels>
      <Descriptions>
        <Description description="" languagecode="1033" />
      </Descriptions>
    </option>
  </options>
</optionset>