<?xml version="1.0" encoding="utf-8"?>
<optionset Name="appbase_hrrequisitionpostingchannel" localizedName="HR Requisition Posting Channel" xmlns:xsi="http://www.w3.org/2001/XMLSchema-instance">
  <OptionSetType>picklist</OptionSetType>
  <IsGlobal>1</IsGlobal>
  <IntroducedVersion>1.0.0.1</IntroducedVersion>
  <IsCustomizable>1</IsCustomizable>
  <displaynames>
    <displayname description="HR Requisition Posting Channel" languagecode="1033" />
  </displaynames>
  <Descriptions>
    <Description description="" languagecode="1033" />
  </Descriptions>
  <options>
    <option value="147130000" ExternalValue="" IsHidden="0">
      <labels>
        <label description="Company Website" languagecode="1033" />
      </labels>
    </option>
    <option value="147130001" ExternalValue="" IsHidden="0">
      <labels>
        <label description="Job Board" languagecode="1033" />
      </labels>
    </option>
    <option value="147130002" ExternalValue="" IsHidden="0">
      <labels>
        <label description="LinkedIn" languagecode="1033" />
      </labels>
    </option>
    <option value="147130003" ExternalValue="" IsHidden="0">
      <labels>
        <label description="Indeed" languagecode="1033" />
      </labels>
    </option>
    <option value="147130004" ExternalValue="" IsHidden="0">
      <labels>
        <label description="Government Jobs Portal" languagecode="1033" />
      </labels>
    </option>
    <option value="147130005" ExternalValue="" IsHidden="0">
      <labels>
        <label description="Professional Association" languagecode="1033" />
      </labels>
    </option>
    <option value="147130006" ExternalValue="" IsHidden="0">
      <labels>
        <label description="Internal Portal" languagecode="1033" />
      </labels>
    </option>
    <option value="147130007" ExternalValue="" IsHidden="0">
      <labels>
        <label description="Campus Recruiting" languagecode="1033" />
      </labels>
    </option>
    <option value="147130008" ExternalValue="" IsHidden="0">
      <labels>
        <label description="Agency" languagecode="1033" />
      </labels>
    </option>
    <option value="147130009" ExternalValue="" IsHidden="0">
      <labels>
        <label description="Employee Referral" languagecode="1033" />
      </labels>
    </option>
  </options>
</optionset>